setup.cfg
setup.py
optimus_ml/__init__.py
optimus_ml.egg-info/PKG-INFO
optimus_ml.egg-info/SOURCES.txt
optimus_ml.egg-info/dependency_links.txt
optimus_ml.egg-info/requires.txt
optimus_ml.egg-info/top_level.txt
optimus_ml/extra/__init__.py
optimus_ml/extra/dual_imputer.py
optimus_ml/extra/fancyprint.py
optimus_ml/extra/forests.py
optimus_ml/extra/neural_network.py
optimus_ml/extra/timeout.py
optimus_ml/optimizer/__init__.py
optimus_ml/optimizer/builder.py
optimus_ml/optimizer/converter.py
optimus_ml/optimizer/model_optimizer.py
optimus_ml/optimizer/multi_optimizer.py
optimus_ml/optimizer/optimizer.py
optimus_ml/vault/__init__.py
optimus_ml/vault/decoder.py
optimus_ml/vault/model_factory.py