Metadata-Version: 1.1
Name: optimus-ml
Version: 0.2
Summary: Automated machine learning tool
Home-page: https://github.com/Yatoom/Optimus
Author: Jeroen van Hoof
Author-email: jeroen@jeroenvanhoof.nl
License: UNKNOWN
Download-URL: https://github.com/Yatoom/Optimus/archive/0.1.tar.gz
Keywords: machine learning,automated machine learning
Platform: UNKNOWN
